bytewax/duckdb/__init__.py
bytewax/duckdb/operators.py
bytewax/duckdb/py.typed
bytewax_duckdb-0.1.22.dist-info/LICENSE.md
bytewax_duckdb-0.1.22.dist-info/METADATA
bytewax_duckdb-0.1.22.dist-info/WHEEL
bytewax_duckdb-0.1.22.dist-info/top_level.txt
bytewax_duckdb-0.1.22.dist-info/RECORD
