Metadata-Version: 2.1
Name: bytewax-duckdb
Version: 0.1.22
Summary: Bytewax custom sink for DuckDB and MotherDuck
Author-email: "Bytewax, Inc." <info@bytewax.io>
License: # Software License Agreement
Project-URL: Homepage, https://github.com/bytewax/bytewax-duckdb
Project-URL: Bug Reports, https://github.com/bytewax/bytewax-duckdb/issues/new
Project-URL: Source, https://github.com/bytewax/bytewax-duckdb/
Keywords: bytewax,streaming,operator
Classifier: Development Status :: 4 - Beta
Classifier: Intended Audience :: Developers
Classifier: Programming Language :: Python :: 3
Classifier: Programming Language :: Python :: 3.9
Classifier: Programming Language :: Python :: 3.10
Classifier: Programming Language :: Python :: 3.11
Classifier: Programming Language :: Python :: 3.12
Classifier: Programming Language :: Python :: 3 :: Only
Requires-Python: >=3.9
License-File: LICENSE.md
Requires-Dist: bytewax>=0.21
Requires-Dist: pyarrow>=17.0.0
Requires-Dist: duckdb==1.1.3
